odoo/addons/ssi_mia_absen_harian_py3o_report/README.rst
odoo/addons/ssi_mia_absen_harian_py3o_report/__init__.py
odoo/addons/ssi_mia_absen_harian_py3o_report/__manifest__.py
odoo/addons/ssi_mia_absen_harian_py3o_report/reports/__init__.py
odoo/addons/ssi_mia_absen_harian_py3o_report/reports/daily_attendance.ods
odoo/addons/ssi_mia_absen_harian_py3o_report/reports/daily_attendance.py
odoo/addons/ssi_mia_absen_harian_py3o_report/reports/daily_attendance_reports.xml
odoo/addons/ssi_mia_absen_harian_py3o_report/security/ir.model.access.csv
odoo/addons/ssi_mia_absen_harian_py3o_report/static/description/icon.png
odoo/addons/ssi_mia_absen_harian_py3o_report/wizards/__init__.py
odoo/addons/ssi_mia_absen_harian_py3o_report/wizards/print_daily_attendance.py
odoo/addons/ssi_mia_absen_harian_py3o_report/wizards/print_daily_attendance_views.xml
odoo14_addon_ssi_mia_absen_harian_py3o_report-14.0.1.0.1.dev3.dist-info/METADATA
odoo14_addon_ssi_mia_absen_harian_py3o_report-14.0.1.0.1.dev3.dist-info/WHEEL
odoo14_addon_ssi_mia_absen_harian_py3o_report-14.0.1.0.1.dev3.dist-info/top_level.txt
odoo14_addon_ssi_mia_absen_harian_py3o_report-14.0.1.0.1.dev3.dist-info/RECORD
