Metadata-Version: 2.1
Name: odoo14-addon-ssi-mia-absen-harian-py3o-report
Version: 14.0.1.0.1.dev3
Summary: Daily Attendance py3o Report
Home-page: https://simetri-sinergi.id
Author: PT. Simetri Sinergi Indonesia, OpenSynergy Indonesia
License: AGPL-3
Platform: UNKNOWN
Classifier: Programming Language :: Python
Classifier: Framework :: Odoo
Classifier: Framework :: Odoo :: 14.0
Classifier: License :: OSI Approved :: GNU Affero General Public License v3
Requires-Python: >=3.6
Requires-Dist: odoo14-addon-report-py3o
Requires-Dist: odoo14-addon-ssi-hr-overtime
Requires-Dist: odoo14-addon-ssi-timesheet-attendance
Requires-Dist: odoo (<14.1dev,>=14.0a)
Requires-Dist: py3o.formats
Requires-Dist: py3o.template
